CHANGES.txt
MANIFEST.in
README.md
setup.py
djinn_forms/__init__.py
djinn_forms/__init__.pyc
djinn_forms/urls.py
djinn_forms/urls.pyc
djinn_forms.egg-info/PKG-INFO
djinn_forms.egg-info/SOURCES.txt
djinn_forms.egg-info/dependency_links.txt
djinn_forms.egg-info/entry_points.txt
djinn_forms.egg-info/not-zip-safe
djinn_forms.egg-info/requires.txt
djinn_forms.egg-info/top_level.txt
djinn_forms/.idea/djinn_forms.iml
djinn_forms/.idea/encodings.xml
djinn_forms/.idea/misc.xml
djinn_forms/.idea/modules.xml
djinn_forms/.idea/vcs.xml
djinn_forms/.idea/workspace.xml
djinn_forms/.idea/scopes/scope_settings.xml
djinn_forms/fields/__init__.py
djinn_forms/fields/__init__.pyc
djinn_forms/fields/base.py
djinn_forms/fields/base.pyc
djinn_forms/fields/image.py
djinn_forms/fields/image.pyc
djinn_forms/fields/keyword.py
djinn_forms/fields/keyword.pyc
djinn_forms/fields/relate.py
djinn_forms/fields/relate.pyc
djinn_forms/fields/role.py
djinn_forms/fields/role.pyc
djinn_forms/fields/share.py
djinn_forms/fields/share.pyc
djinn_forms/forms/__init__.py
djinn_forms/forms/__init__.pyc
djinn_forms/forms/relate.py
djinn_forms/forms/relate.pyc
djinn_forms/forms/richtext.py
djinn_forms/forms/richtext.pyc
djinn_forms/forms/share.py
djinn_forms/forms/share.pyc
djinn_forms/locale/en_EN/LC_MESSAGES/django.mo
djinn_forms/locale/en_EN/LC_MESSAGES/django.po
djinn_forms/locale/nl_NL/LC_MESSAGES/django.mo
djinn_forms/locale/nl_NL/LC_MESSAGES/django.po
djinn_forms/static/css/djinn_forms.css
djinn_forms/static/css/djinn_forms_keyword.css
djinn_forms/static/img/img.png
djinn_forms/static/img/link.png
djinn_forms/static/js/djinn_forms.js
djinn_forms/static/js/djinn_forms_datetimedirect.js
djinn_forms/static/js/djinn_forms_keyword.js
djinn_forms/static/js/djinn_forms_link.js
djinn_forms/static/js/djinn_forms_relate.js
djinn_forms/static/js/djinn_forms_richtext.js
djinn_forms/templates/djinn_forms/snippets/contentimages.html
djinn_forms/templates/djinn_forms/snippets/contentlinks.html
djinn_forms/templates/djinn_forms/snippets/contentsearch.html
djinn_forms/templates/djinn_forms/snippets/datetimedirectwidget.html
djinn_forms/templates/djinn_forms/snippets/datetimewidget.html
djinn_forms/templates/djinn_forms/snippets/documentattachmentwidget.html
