Metadata-Version: 1.1
Name: djinn-forms
Version: 1.3.4
Summary: Djinn Intranet Forms
Home-page: https://github.com/PythonUnited/djinn-forms
Author: PythonUnited
Author-email: info@pythonunited.com
License: beer-ware
Keywords: Djinn forms
Platform: UNKNOWN
Classifier: Development Status :: 5 - Production/Stable
Classifier: Framework :: Django
Classifier: Intended Audience :: Developers
Classifier: License :: Freely Distributable
Classifier: Programming Language :: Python
Classifier: Topic :: Internet :: WWW/HTTP :: Site Management
Classifier: Topic :: Software Development :: Libraries :: Application Frameworks
